{
  "dealer": {
    "partition_name": "AllDisk",
    "group_name": "AnalysisOps",
    "copy_op": {
      "module": "PhEDExCopyInterface",
      "config": {
        "chunk_size": 50
      }
    },
    "plugins": {
      "enforcer": {
        "priority": 1,
        "module": "EnforcerHandler",
        "config": {
          "enforcer": {
            "max_dataset_size": 50.0,
            "policy": "/home/yiiyama/ddm/dynamo-policies/common/enforcer_rules_alldisk.json"
          }
        }
      }
    },
    "attrs": {},
    "target_sites": ["T1_*_Disk", "T2_*"],
    "target_site_occupancy": 1.0,
    "max_site_pending_fraction": 1.0,
    "max_total_cycle_volume": 100
  },
  "log_level": "info"
}
